zabbixsim/__init__.py
zabbixsim/zabbixrec.py
zabbixsim/zabbixsim.py
zabbixsim-0.3.0.dist-info/LICENSE
zabbixsim-0.3.0.dist-info/METADATA
zabbixsim-0.3.0.dist-info/WHEEL
zabbixsim-0.3.0.dist-info/entry_points.txt
zabbixsim-0.3.0.dist-info/top_level.txt
zabbixsim-0.3.0.dist-info/RECORD
