Metadata-Version: 2.1
Name: zabbixsim
Version: 0.3.0
Summary: Zabbix Agent simulator
Home-page: https://github.com/adamleggo/zabbixsim
Author: Adam Leggo
Author-email: adam@leggo.id.au
Maintainer: Adam Leggo <adam@leggo.id.au>
License: MIT
Platform: UNKNOWN
Classifier: Development Status :: 4 - Beta
Classifier: Environment :: Console
Classifier: Intended Audience :: Developers
Classifier: Intended Audience :: Information Technology
Classifier: Intended Audience :: System Administrators
Classifier: Intended Audience :: Telecommunications Industry
Classifier: License :: OSI Approved :: MIT License
Classifier: Programming Language :: Python :: 3
Classifier: Programming Language :: Python :: 3.6
Classifier: Topic :: Communications
Classifier: Topic :: System :: Monitoring
Classifier: Topic :: System :: Networking :: Monitoring
License-File: LICENSE
Requires-Dist: zabbix-api (>=0.5.4)
Requires-Dist: pyyaml
